textra_api_wrapper/__init__.py
textra_api_wrapper/api_client.py
textra_api_wrapper/api_response_parser.py
textra_api_wrapper/base_client.py
textra_api_wrapper/log.py
textra_api_wrapper-0.4.0.dist-info/METADATA
textra_api_wrapper-0.4.0.dist-info/WHEEL
textra_api_wrapper-0.4.0.dist-info/licenses/LICENSE
textra_api_wrapper-0.4.0.dist-info/RECORD
