Metadata-Version: 2.3
Name: textra-api-wrapper
Version: 0.4.0
Summary: textraの翻訳APIラッパー
Author-email: atu4403 <73111778+atu4403@users.noreply.github.com>
License-File: LICENSE
Requires-Python: >=3.8
Requires-Dist: aiofiles>=24.1.0
Requires-Dist: aiohttp-oauthlib>=0.1.0
Requires-Dist: aiohttp>=3.9.5
Requires-Dist: oauthlib>=3.2.2
Requires-Dist: requests-oauthlib>=2.0.0
Requires-Dist: requests>=2.32.3
Requires-Dist: rich>=13.7.1
